betsi/__init__.py
betsi/_version.py
betsi/models.py
betsi/predictors.py
betsi/preprocessors.py
betsi_ml-0.0.4.dist-info/LICENSE
betsi_ml-0.0.4.dist-info/METADATA
betsi_ml-0.0.4.dist-info/WHEEL
betsi_ml-0.0.4.dist-info/top_level.txt
betsi_ml-0.0.4.dist-info/RECORD
